aikitchen/__init__.py
aikitchen/exceptions.py
aikitchen/image.py
aikitchen/login.py
aikitchen/music.py
AIKitchen_API-0.2.0.dist-info/METADATA
AIKitchen_API-0.2.0.dist-info/WHEEL
AIKitchen_API-0.2.0.dist-info/entry_points.txt
AIKitchen_API-0.2.0.dist-info/top_level.txt
AIKitchen_API-0.2.0.dist-info/RECORD
